nessai/__init__.py
nessai/config.py
nessai/evidence.py
nessai/flowsampler.py
nessai/livepoint.py
nessai/model.py
nessai/nestedsampler.py
nessai/plot.py
nessai/posterior.py
nessai/priors.py
nessai/stopping_criteria.py
nessai/experimental/__init__.py
nessai/experimental/flowmodel/__init__.py
nessai/experimental/flowmodel/clustering.py
nessai/experimental/flows/__init__.py
nessai/experimental/flows/glasflow.py
nessai/experimental/gw/__init__.py
nessai/experimental/gw/proposal.py
nessai/experimental/proposal/__init__.py
nessai/experimental/proposal/clustering.py
nessai/experimental/proposal/mcmc/__init__.py
nessai/experimental/proposal/mcmc/proposal.py
nessai/experimental/proposal/mcmc/steps.py
nessai/experimental/proposal/mcmc/utils.py
nessai/flowmodel/__init__.py
nessai/flowmodel/base.py
nessai/flowmodel/config.py
nessai/flowmodel/importance.py
nessai/flowmodel/utils.py
nessai/flows/__init__.py
nessai/flows/base.py
nessai/flows/distributions.py
nessai/flows/maf.py
nessai/flows/nets.py
nessai/flows/nsf.py
nessai/flows/realnvp.py
nessai/flows/transforms.py
nessai/flows/utils.py
nessai/gw/__init__.py
nessai/gw/proposal.py
nessai/gw/reparameterisations.py
nessai/gw/utils.py
nessai/proposal/__init__.py
nessai/proposal/analytic.py
nessai/proposal/augmented.py
nessai/proposal/base.py
nessai/proposal/importance.py
nessai/proposal/rejection.py
nessai/proposal/utils.py
nessai/proposal/flowproposal/__init__.py
nessai/proposal/flowproposal/base.py
nessai/proposal/flowproposal/flowproposal.py
nessai/reparameterisations/__init__.py
nessai/reparameterisations/angle.py
nessai/reparameterisations/base.py
nessai/reparameterisations/combined.py
nessai/reparameterisations/discrete.py
nessai/reparameterisations/null.py
nessai/reparameterisations/rescale.py
nessai/reparameterisations/utils.py
nessai/samplers/__init__.py
nessai/samplers/base.py
nessai/samplers/importancesampler.py
nessai/samplers/nestedsampler.py
nessai/utils/__init__.py
nessai/utils/bilbyutils.py
nessai/utils/distance.py
nessai-0.15.1.dist-info/licenses/LICENSE.md
nessai-0.15.1.dist-info/METADATA
nessai-0.15.1.dist-info/WHEEL
nessai-0.15.1.dist-info/top_level.txt
nessai-0.15.1.dist-info/RECORD
