Metadata-Version: 2.4
Name: nessai
Version: 0.15.1
Summary: Nessai: Nested Sampling with Artificial Intelligence
Author-email: "Michael J. Williams" <michaeljw1@googlemail.com>
License: MIT
Project-URL: Homepage, https://github.com/mj-will/nessai
Project-URL: Documentation, https://nessai.readthedocs.io/
Keywords: nested sampling,normalizing flows,machine learning
Classifier: Programming Language :: Python :: 3
Classifier: License :: OSI Approved :: MIT License
Classifier: Operating System :: OS Independent
Requires-Python: >=3.9
License-File: LICENSE.md
Requires-Dist: glasflow
Requires-Dist: h5py>=3.0
Requires-Dist: matplotlib>=2.0
Requires-Dist: numpy>=1.9
Requires-Dist: pandas
Requires-Dist: scipy>0.16
Requires-Dist: seaborn
Requires-Dist: torch>=1.11.0
Requires-Dist: importlib-metadata; python_version < "3.10"
Provides-Extra: test
Requires-Dist: pytest; extra == "test"
Requires-Dist: pytest-cov; extra == "test"
Requires-Dist: pytest-timeout; extra == "test"
Requires-Dist: pytest-rerunfailures; extra == "test"
Requires-Dist: pytest-integration; extra == "test"
Provides-Extra: gw
Requires-Dist: lalsuite; sys_platform != "win32" and extra == "gw"
Requires-Dist: bilby; extra == "gw"
Requires-Dist: astropy; extra == "gw"
Provides-Extra: clustering
Requires-Dist: faiss-cpu>=1.7.3; extra == "clustering"
Provides-Extra: dev
Requires-Dist: pre-commit; extra == "dev"
Requires-Dist: ray[default]; (sys_platform != "win32" and python_version < "3.12") and extra == "dev"
Requires-Dist: multiprocess; extra == "dev"
Requires-Dist: corner; extra == "dev"
Requires-Dist: ruff; extra == "dev"
Requires-Dist: faiss-cpu; extra == "dev"
Provides-Extra: docs
Requires-Dist: sphinx; extra == "docs"
Requires-Dist: sphinx_rtd_theme; extra == "docs"
Requires-Dist: numpydoc; extra == "docs"
Requires-Dist: sphinx-autoapi; extra == "docs"
Provides-Extra: nflows
Requires-Dist: nflows; extra == "nflows"
Dynamic: license-file
